vibe_helloworld/__init__.py
vibe_helloworld/_version.py
vibe_helloworld/generator.py
vibe_helloworld/py.typed
vibe_helloworld-0.1.1.dist-info/METADATA
vibe_helloworld-0.1.1.dist-info/WHEEL
vibe_helloworld-0.1.1.dist-info/licenses/LICENSE
vibe_helloworld-0.1.1.dist-info/RECORD
