Metadata-Version: 2.4
Name: vibe-helloworld
Version: 0.1.1
Summary: AI-powered Hello World generator - A fun project that uses AI to output Hello World
Project-URL: Homepage, https://github.com/cloxl/vibe-helloworld
Project-URL: Repository, https://github.com/cloxl/vibe-helloworld
Project-URL: Issues, https://github.com/cloxl/vibe-helloworld/issues
Author-email: cloxl <cloxl@cloxl.com>
License-File: LICENSE
Classifier: Development Status :: 4 - Beta
Classifier: Intended Audience :: Developers
Classifier: License :: OSI Approved :: MIT License
Classifier: Programming Language :: Python :: 3
Classifier: Programming Language :: Python :: 3.10
Classifier: Programming Language :: Python :: 3.11
Classifier: Programming Language :: Python :: 3.12
Classifier: Topic :: Software Development :: Libraries :: Python Modules
Classifier: Topic :: Text Processing :: General
Classifier: Typing :: Typed
Requires-Python: >=3.10
Requires-Dist: aiohttp>=3.9.0
Provides-Extra: dev
Requires-Dist: black>=23.0.0; extra == 'dev'
Requires-Dist: pytest-asyncio>=0.21.0; extra == 'dev'
Requires-Dist: pytest>=7.0.0; extra == 'dev'
Requires-Dist: ruff>=0.1.0; extra == 'dev'
